humo/__init__.py
humo/__version__.py
humo/ImageAnalysis/PennateAngle.py
humo/ImageAnalysis/VideoConverter.py
humo/ImageAnalysis/__init__.py
humo/ImageAnalysis/utilitymod.py
humo/Preprocess/PreProcess.py
humo/Preprocess/_PreProcess.py
humo/Preprocess/__init__.py
humo/Preprocess/mmt_process_main.py
humo/Preprocess/mvc_process.py
humo/Preprocess/processing/MMT_Error_msg.py
humo/Preprocess/processing/MVCprocess.py
humo/Preprocess/processing/__init__.py
humo/Preprocess/processing/_processor.py
humo/Preprocess/processing/mmt_processor.py
humo/Preprocess/processing/processor.py
humo/Setuptools/__init__.py
humo/Stats/__init__.py
humo/Stats/anova_model.py
humo/Stats/equalvaliance.py
humo/Stats/multi_group_comparison.py
humo/Stats/normality.py
humo/Stats/read_csv.py
humo/Stats/statsfig.py
humo/Stats/statsresult.py
humo/Stats/two_group_comparison.py
humo/Stats/sample/gapminder.csv
humo/Stats/sample/oneway_RManova.csv
humo/Stats/sample/oneway_anova2.csv
humo/Stats/sample/paired_ttest.csv
humo/Stats/sample/twoway_RManova.csv
humo/Stats/sample/twoway_anova.csv
humo/Stats/sample/twoway_split_anova1.csv
humo/Stats/sample/unpaired_ttest.csv
humo/dataIO/IO.py
humo/dataIO/__init__.py
humo/dataIO/path.py
humo/dataIO/settings.py
humo/dataIO/processor/__init__.py
humo/dataIO/processor/processor.py
humo/mechanics/__init__.py
humo/mechanics/STS4link/__init__.py
humo/mechanics/STS4link/force_term.py
humo/mechanics/STS4link/gravity_term.py
humo/mechanics/STS4link/main.py
humo/mechanics/STS4link/mass_matrix.py
humo/mechanics/STS4link/sitmodel.py
humo/mechanics/STS4link/velocity_term.py
humo/mechanics/sittingmodel/__init__.py
humo/mechanics/sittingmodel/calc_sitting_data.py
humo/mechanics/sittingmodel/sittingEOM.py
humo/mechanics/sittingmodel/sittingmodel.py
humo/motion/__init__.py
humo/motion/Piano/__init__.py
humo/motion/Piano/figtools.py
humo/motion/Piano/piano_analysis.py
humo/motion/Piano/tools.py
humo/motion/Piano/processor/__init__.py
humo/motion/Piano/processor/analysis_section.py
humo-1.5.1.40.dist-info/METADATA
humo-1.5.1.40.dist-info/WHEEL
humo-1.5.1.40.dist-info/entry_points.txt
humo-1.5.1.40.dist-info/top_level.txt
humo-1.5.1.40.dist-info/RECORD
