Metadata-Version: 2.1
Name: humo
Version: 1.5.1.40
Summary: A toolkit for non-programmer to wrangle the motion data measured by 3D motion analyzer
Home-page: https://sites.google.com/view/pythonforeveryone/python-for-evryone
Author: Akira Kobayashi
Author-email: 1991003n@spu.ac.jp
License: MIT
Platform: UNKNOWN
Classifier: Development Status :: 3 - Alpha
Classifier: Programming Language :: Python
Classifier: Intended Audience :: Developers
Classifier: Operating System :: POSIX
Classifier: Programming Language :: Python :: 3.7
